setup.py
prime_finder/__init__.py
prime_finder/prime_finder.py
prime_finder/timer.py
prime_finder.egg-info/PKG-INFO
prime_finder.egg-info/SOURCES.txt
prime_finder.egg-info/dependency_links.txt
prime_finder.egg-info/not-zip-safe
prime_finder.egg-info/top_level.txt