Metadata-Version: 1.0
Name: prime-finder
Version: 0.1
Summary: Uses the Sieve of Erasthenes to find prime factors of any number given.
Home-page: https://github.com/hammacktony/Prime_Finder.git
Author: Tony Hammack
Author-email: hammack.tony@gmail.com
License: MIT
Platform: UNKNOWN
